chat_ui/__init__.py
chat_ui/chat_widget.py
chat_ui/static/index.js
chat_ui/static/styles.css
chat_ui-1.2.2.dist-info/METADATA
chat_ui-1.2.2.dist-info/WHEEL
chat_ui-1.2.2.dist-info/RECORD
