Metadata-Version: 2.4
Name: chat_ui
Version: 1.2.2
Requires-Dist: anywidget
Requires-Dist: markdown
Requires-Dist: pandas
Requires-Dist: traitlets
